freeride/__init__.py
freeride/affine.py
freeride/base.py
freeride/costs.py
freeride/curves.py
freeride/double_auction.py
freeride/equilibrium.py
freeride/exceptions.py
freeride/formula.py
freeride/games.py
freeride/monopoly.py
freeride/plotting.py
freeride/quadratic.py
freeride/revenue.py
freeride-0.1.1.dist-info/licenses/LICENSE
tests/__init__.py
tests/test_auction.py
tests/test_curves.py
tests/test_equilibrium.py
tests/test_formula.py
tests/test_games.py
tests/test_horizontal_curves.py
tests/test_intersection_operator.py
tests/test_longrun.py
tests/test_monopoly.py
tests/test_plotting.py
tests/test_quadratic_element.py
tests/test_world_price.py
freeride-0.1.1.dist-info/METADATA
freeride-0.1.1.dist-info/WHEEL
freeride-0.1.1.dist-info/top_level.txt
freeride-0.1.1.dist-info/RECORD
