Metadata-Version: 2.4
Name: freeride
Version: 0.1.1
Summary: A package for undergraduate microeconomics.
Home-page: https://github.com/alexanderthclark/FreeRide
Author: Alexander Clark
Author-email: 
Requires-Python: >=3.8
License-File: LICENSE
Requires-Dist: matplotlib
Requires-Dist: numpy
Requires-Dist: papermill
Requires-Dist: IPython
Requires-Dist: bokeh
Dynamic: author
Dynamic: description
Dynamic: description-content-type
Dynamic: home-page
Dynamic: license-file
Dynamic: requires-dist
Dynamic: requires-python
Dynamic: summary
